MANIFEST.in
README.md
setup.py
django_datatable.egg-info/PKG-INFO
django_datatable.egg-info/SOURCES.txt
django_datatable.egg-info/dependency_links.txt
django_datatable.egg-info/not-zip-safe
django_datatable.egg-info/requires.txt
django_datatable.egg-info/top_level.txt
table/__init__.py
table/forms.py
table/models.py
table/tables.py
table/urls.py
table/utils.py
table/views.py
table/widgets.py
table/columns/__init__.py
table/columns/base.py
table/columns/calendarcolumn.py
table/columns/checkboxcolumn.py
table/columns/datetimecolumn.py
table/columns/linkcolumn.py
table/columns/sequencecolumn.py
table/static/css/datatable.bootstrap.css
table/static/fonts/glyphicons-halflings-regular.eot
table/static/fonts/glyphicons-halflings-regular.svg
table/static/fonts/glyphicons-halflings-regular.ttf
table/static/fonts/glyphicons-halflings-regular.woff
table/static/images/Sorting icons.psd
table/static/images/back_disabled.png
table/static/images/back_enabled.png
table/static/images/back_enabled_hover.png
table/static/images/favicon.ico
table/static/images/forward_disabled.png
table/static/images/forward_enabled.png
table/static/images/forward_enabled_hover.png
table/static/images/sort_asc.png
table/static/images/sort_asc_disabled.png
table/static/images/sort_both.png
table/static/images/sort_desc.png
table/static/images/sort_desc_disabled.png
table/static/js/bootstrap.dataTables.js
table/static/js/dataTables.fixedColumns.min.js
table/static/js/jquery.browser.min.js
table/static/js/jquery.dataTables.min.js
table/templates/table/simple_table.html
table/templates/table/table.html
table/templatetags/__init__.py
table/templatetags/table_tags.py
table/tests/__init__.py
table/tests/test_columns.py
table/tests/test_tables.py
table/tests/test_utils.py
table/tests/test_views.py
table/tests/test_widgets.py